[
   {
      "id":"0",
      "author":"Alejandro Escamilla",
      "width":5000,
      "height":3333,
      "url":"http://localhost:8080/photos/1.jpg"
   },
   {
      "id":"1",
      "author":"Alejandro Escamilla",
      "width":5000,
      "height":3333,
      "url":"http://localhost:8080/photos/2.jpg"
   },
   {
      "id":"2",
      "author":"Alejandro Escamilla",
      "width":5000,
      "height":3333,
      "url":"http://localhost:8080/photos/3.jpg"
   },
   {
      "id":"3",
      "author":"Alejandro Escamilla",
      "width":5000,
      "height":3333,
      "url":"http://localhost:8080/photos/4.jpg"
   },
   {
      "id":"4",
      "author":"Alejandro Escamilla",
      "width":5000,
      "height":3333,
      "url":"http://localhost:8080/photos/5.jpg"
   }
]